CHANGELOG.txt
LICENCE.txt
MANIFEST.in
README.txt
setup.py
exodigital.egg-info/PKG-INFO
exodigital.egg-info/SOURCES.txt
exodigital.egg-info/dependency_links.txt
exodigital.egg-info/not-zip-safe
exodigital.egg-info/requires.txt
exodigital.egg-info/top_level.txt
exoticwondrous/__init__.py
exoticwondrous/exodigitl.dll
exoticwondrous/exodigitl32.dll
exoticwondrous/jsonex.py