Metadata-Version: 2.1
Name: exodigital
Version: 0.0.1
Summary: A digital clock with displays the weather and temperature of local and global cities
Home-page: https://t.me/exoticwondrous
Author: Ahmed Mohammed
Author-email: ahmdsmhmmd@gmail.com
License: MIT
Keywords: Exo digital clock
Classifier: Development Status :: 5 - Production/Stable
Classifier: Intended Audience :: Education
Classifier: Intended Audience :: Developers
Classifier: Intended Audience :: End Users/Desktop
Classifier: Operating System :: Microsoft :: Windows
Classifier: License :: OSI Approved :: MIT License
Classifier: Programming Language :: Python :: 3
License-File: LICENCE.txt
